pyiotb/__init__.py
pyiotb/client.py
pyiotb/scripts/download_logs.py
pyiotb/scripts/trigger_comparison.py
pyiotb-0.1.3.dist-info/licenses/LICENSE
pyiotb-0.1.3.dist-info/METADATA
pyiotb-0.1.3.dist-info/WHEEL
pyiotb-0.1.3.dist-info/entry_points.txt
pyiotb-0.1.3.dist-info/top_level.txt
pyiotb-0.1.3.dist-info/RECORD
