Metadata-Version: 2.4
Name: pyiotb
Version: 0.1.3
Summary: A library for interfacing to Tartabit IoT Bridge
Author-email: "Tartabit, LLC" <support@tartabit.com>
License: MIT
Project-URL: Homepage, https://github.com/tartabit/iotb-py
Classifier: Programming Language :: Python :: 3
Classifier: License :: OSI Approved :: MIT License
Classifier: Operating System :: OS Independent
Requires-Python: >=3.6
License-File: LICENSE
Requires-Dist: requests
Dynamic: license-file
